studio/artifacts/__init__.py
studio/artifacts/artifact.py
studio/artifacts/artifacts_tracker.py
studio/credentials/__init__.py
studio/credentials/credentials.py
studio/db_providers/__init__.py
studio/db_providers/db_provider_setup.py
studio/db_providers/keyvalue_provider.py
studio/db_providers/local_db_provider.py
studio/db_providers/s3_provider.py
studio/dependencies_policies/__init__.py
studio/dependencies_policies/dependencies_policy.py
studio/dependencies_policies/studio_dependencies_policy.py
studio/experiments/__init__.py
studio/experiments/experiment.py
studio/payload_builders/__init__.py
studio/payload_builders/payload_builder.py
studio/payload_builders/unencrypted_payload_builder.py
studio/queues/__init__.py
studio/queues/local_queue.py
studio/queues/qclient_cache.py
studio/queues/queues_setup.py
studio/queues/rabbit_queue.py
studio/queues/sqs_queue.py
studio/storage/__init__.py
studio/storage/http_storage_handler.py
studio/storage/local_storage_handler.py
studio/storage/s3_storage_handler.py
studio/storage/storage_handler.py
studio/storage/storage_handler_factory.py
studio/storage/storage_setup.py
studio/storage/storage_type.py
studio/storage/storage_util.py
studio/util/__init__.py
studio/util/gpu_util.py
studio/util/logs.py
studio/util/util.py
studioml_cs-0.0.48.post3.data/data/test_requirements-cs.txt
studioml_cs-0.0.48.post3.data/scripts/studio-local-worker
studioml_cs-0.0.48.post3.dist-info/LICENSE
studioml_cs-0.0.48.post3.dist-info/METADATA
studioml_cs-0.0.48.post3.dist-info/WHEEL
studioml_cs-0.0.48.post3.dist-info/top_level.txt
studioml_cs-0.0.48.post3.dist-info/RECORD
