Metadata-Version: 2.1
Name: studioml-cs
Version: 0.0.48.post3
Summary: Base packages for StudioML functionality
Home-page: https://github.com/studioml/studio
Author: Andrei Denissov
Author-email: andrei.denissov@gmail.com
License: Apache License, Version 2.0
Keywords: studioml StudioML Studio
Platform: UNKNOWN
Classifier: Development Status :: 4 - Beta
Classifier: Environment :: Console
Classifier: Intended Audience :: Developers
Classifier: Intended Audience :: Science/Research
Classifier: Operating System :: POSIX :: Linux
Classifier: Programming Language :: Python :: 3.8
Classifier: Topic :: Scientific/Engineering :: Artificial Intelligence
Classifier: Topic :: Utilities
Classifier: License :: OSI Approved :: Apache Software License
Requires-Python: >=3.8
License-File: LICENSE
Requires-Dist: pip
Requires-Dist: setuptools-scm
Requires-Dist: configparser
Requires-Dist: requests
Requires-Dist: PyYAML
Requires-Dist: pyhocon
Requires-Dist: boto3
Requires-Dist: filelock
Requires-Dist: pika (>=1.1.0)
